fastscode/__init__.py
fastscode/fastscode.py
fastscode/simulate.py
fastscode/utils.py
fastscode/worker.py
fastscode/inference/__init__.py
fastscode/inference/inference.py
fastscode/inference/utils.py
fastscode-0.0.8.dist-info/licenses/LICENSE
fastscode-0.0.8.dist-info/METADATA
fastscode-0.0.8.dist-info/WHEEL
fastscode-0.0.8.dist-info/top_level.txt
fastscode-0.0.8.dist-info/RECORD
