Metadata-Version: 2.4
Name: fastscode
Version: 0.0.8
Summary: FastSCODE
Author: Complex Intelligent Systems Laboratory (CISLAB)
Author-email: rakbin007@naver.com
License: BSD-3-Clause
License-File: LICENSE
Requires-Dist: numpy
Requires-Dist: statsmodels
Requires-Dist: networkx
Requires-Dist: tqdm
Requires-Dist: matplotlib
Requires-Dist: omegaconf
Requires-Dist: fasttenet
Requires-Dist: scikit-learn
Dynamic: author
Dynamic: author-email
Dynamic: description
Dynamic: description-content-type
Dynamic: license
Dynamic: license-file
Dynamic: requires-dist
Dynamic: summary
